setup.cfg
setup.py
reba/__init__.py
reba/api/HttpUtils.py
reba/api/Reba.py
reba/api/__init__.py
reba_sms_python_sdk.egg-info/PKG-INFO
reba_sms_python_sdk.egg-info/SOURCES.txt
reba_sms_python_sdk.egg-info/dependency_links.txt
reba_sms_python_sdk.egg-info/requires.txt
reba_sms_python_sdk.egg-info/top_level.txt