Metadata-Version: 1.0
Name: reba-sms-python-sdk
Version: 1.0.0
Summary: reba python sdk
Home-page: UNKNOWN
Author: shomop
Author-email: lanran@shomop.com
License: MIT
Keywords: reba,sms,sdk
Platform: any
